dbbs_catalogue/__init__.py
dbbs_catalogue/mods/.gitkeep
dbbs_catalogue/mods/arbor/CaL13__0.mod
dbbs_catalogue/mods/arbor/Ca__0.mod
dbbs_catalogue/mods/arbor/Cav2_1__0.mod
dbbs_catalogue/mods/arbor/Cav2_2__0.mod
dbbs_catalogue/mods/arbor/Cav2_3__0.mod
dbbs_catalogue/mods/arbor/Cav3_1__0.mod
dbbs_catalogue/mods/arbor/Cav3_2__0.mod
dbbs_catalogue/mods/arbor/Cav3_3__0.mod
dbbs_catalogue/mods/arbor/HCN1__0.mod
dbbs_catalogue/mods/arbor/HCN1__golgi.mod
dbbs_catalogue/mods/arbor/HCN2__0.mod
dbbs_catalogue/mods/arbor/Kca1_1__0.mod
dbbs_catalogue/mods/arbor/Kca2_2__0.mod
dbbs_catalogue/mods/arbor/Kca3_1__0.mod
dbbs_catalogue/mods/arbor/Kir2_3__0.mod
dbbs_catalogue/mods/arbor/Km__0.mod
dbbs_catalogue/mods/arbor/Kv1_1__0.mod
dbbs_catalogue/mods/arbor/Kv1_5__0.mod
dbbs_catalogue/mods/arbor/Kv2_2__0.mod
dbbs_catalogue/mods/arbor/Kv3_3__0.mod
dbbs_catalogue/mods/arbor/Kv3_4__0.mod
dbbs_catalogue/mods/arbor/Kv4_3__0.mod
dbbs_catalogue/mods/arbor/Kv7__0.mod
dbbs_catalogue/mods/arbor/Leak__0.mod
dbbs_catalogue/mods/arbor/Leak__GABA.mod
dbbs_catalogue/mods/arbor/Na__granule_cell.mod
dbbs_catalogue/mods/arbor/Na__granule_cell_FHF.mod
dbbs_catalogue/mods/arbor/Nav1_1__0.mod
dbbs_catalogue/mods/arbor/Nav1_6__0.mod
dbbs_catalogue/mods/arbor/cdp5__0.mod
dbbs_catalogue/mods/arbor/cdp5__CAM.mod
dbbs_catalogue/mods/arbor/cdp5__CAM_GoC.mod
dbbs_catalogue/mods/arbor/cdp5__CR.mod
dbbs_catalogue/mods/neuron/AMPA__0.mod
dbbs_catalogue/mods/neuron/AMPA__autistic.mod
dbbs_catalogue/mods/neuron/AMPA__granule.mod
dbbs_catalogue/mods/neuron/CaL13__0.mod
dbbs_catalogue/mods/neuron/Ca__granule_cell.mod
dbbs_catalogue/mods/neuron/Cav1_2__0.mod
dbbs_catalogue/mods/neuron/Cav1_3__0.mod
dbbs_catalogue/mods/neuron/Cav2_1__0.mod
dbbs_catalogue/mods/neuron/Cav2_2__0.mod
dbbs_catalogue/mods/neuron/Cav2_3__0.mod
dbbs_catalogue/mods/neuron/Cav3_1__0.mod
dbbs_catalogue/mods/neuron/Cav3_2__0.mod
dbbs_catalogue/mods/neuron/Cav3_3__0.mod
dbbs_catalogue/mods/neuron/GABA__0.mod
dbbs_catalogue-6.0.1.dist-info/entry_points.txt
dbbs_catalogue-6.0.1.dist-info/licenses/LICENSE
dbbs_catalogue-6.0.1.dist-info/WHEEL
dbbs_catalogue-6.0.1.dist-info/METADATA
dbbs_catalogue-6.0.1.dist-info/RECORD
