Metadata-Version: 2.4
Name: dbbs-catalogue
Version: 6.0.1
Summary: DBBS NMODL Catalogue
Author-email: Robin De Schepper <robin@alexandria.sc>
License-File: LICENSE
Requires-Dist: nmodl-glia>=7.0
